django_mssql-1.8.dist-info/DESCRIPTION.rst
django_mssql-1.8.dist-info/METADATA
django_mssql-1.8.dist-info/RECORD
django_mssql-1.8.dist-info/WHEEL
django_mssql-1.8.dist-info/metadata.json
django_mssql-1.8.dist-info/top_level.txt
sqlserver_ado/__init__.py
sqlserver_ado/ado_consts.py
sqlserver_ado/base.py
sqlserver_ado/compiler.py
sqlserver_ado/creation.py
sqlserver_ado/dbapi.py
sqlserver_ado/expressions.py
sqlserver_ado/features.py
sqlserver_ado/fields.py
sqlserver_ado/introspection.py
sqlserver_ado/operations.py
sqlserver_ado/patches.py
sqlserver_ado/regex_clr.dll
sqlserver_ado/schema.py
sqlserver_ado/models/__init__.py
sqlserver_ado/models/manager.py
sqlserver_ado/models/query.py
sqlserver_ado/sql_app/__init__.py
sqlserver_ado/sql_app/management/__init__.py
sqlserver_ado/sql_app/management/commands/__init__.py
sqlserver_ado/sql_app/management/commands/install_regex_clr.py
