Metadata-Version: 1.1
Name: django-mssql
Version: 1.8
Summary: Django backend database support for MS SQL Server.
Home-page: https://bitbucket.org/Manfre/django-mssql
Author: Michael Manfre
Author-email: mmanfre@gmail.com
License: MIT
Platform: UNKNOWN
Classifier: Development Status :: 5 - Production/Stable
Classifier: Framework :: Django
Classifier: Framework :: Django :: 1.8
Classifier: Programming Language :: Python
Classifier: Programming Language :: Python :: 2.7
Classifier: Programming Language :: Python :: 3.4
Classifier: Topic :: Internet :: WWW/HTTP
